MANIFEST.in
setup.py
anthill/dlc/__init__.py
anthill/dlc/admin.py
anthill/dlc/handler.py
anthill/dlc/options.py
anthill/dlc/server.py
anthill/dlc/model/__init__.py
anthill/dlc/model/apps.py
anthill/dlc/model/bundle.py
anthill/dlc/model/data.py
anthill/dlc/model/deploy.py
anthill/dlc/sql/application_versions.sql
anthill/dlc/sql/applications.sql
anthill/dlc/sql/bundles.sql
anthill/dlc/sql/data_bundles.sql
anthill/dlc/sql/datas.sql
anthill_dlc.egg-info/PKG-INFO
anthill_dlc.egg-info/SOURCES.txt
anthill_dlc.egg-info/dependency_links.txt
anthill_dlc.egg-info/namespace_packages.txt
anthill_dlc.egg-info/not-zip-safe
anthill_dlc.egg-info/requires.txt
anthill_dlc.egg-info/top_level.txt