Metadata-Version: 1.0
Name: anthill-dlc
Version: 0.2
Summary: Downloadable content (DLC) management service for Anthill platform
Home-page: https://github.com/anthill-platform/anthill-dlc
Author: desertkun
Author-email: desertkun@gmail.com
License: MIT
Platform: UNKNOWN
